LICENSE
README.md
setup.cfg
setup.py
UNISIMConnect/__init__.py
UNISIMConnect/constants.py
UNISIMConnect/unisim_connect.py
UNISIM_connector.egg-info/PKG-INFO
UNISIM_connector.egg-info/SOURCES.txt
UNISIM_connector.egg-info/dependency_links.txt
UNISIM_connector.egg-info/requires.txt
UNISIM_connector.egg-info/top_level.txt